lookslike/__init__.py
lookslike/utils.py
lookslike/_sep/__init__.py
lookslike/_sep/like.py
lookslike-1.1.0.dist-info/LICENSE
lookslike-1.1.0.dist-info/METADATA
lookslike-1.1.0.dist-info/WHEEL
lookslike-1.1.0.dist-info/top_level.txt
lookslike-1.1.0.dist-info/RECORD
